rlt/uart_rx.v

module uart_rx (

    input  wire clk,
    input  wire rst,
    input  wire rx,

    output reg [7:0] rx_data,
    output reg rx_done

);

parameter CLKS_PER_BIT = 4;

reg [15:0] clk_count;
reg [3:0]  bit_index;
reg [7:0]  data_reg;

reg receiving;

always @(posedge clk) begin

    if (rst) begin

        clk_count <= 0;
        bit_index <= 0;
        data_reg  <= 0;
        rx_data   <= 0;
        rx_done   <= 0;
        receiving <= 0;

    end

    else begin

        rx_done <= 0;

        // Detect start bit
        if (!receiving && rx == 0) begin

            receiving <= 1;
            clk_count <= 0;
            bit_index <= 0;

        end

        // Receive data
        else if (receiving) begin

            if (clk_count < CLKS_PER_BIT - 1) begin

                clk_count <= clk_count + 1;

            end

            else begin

                clk_count <= 0;

                if (bit_index < 8) begin

                    data_reg[bit_index] <= rx;
                    bit_index <= bit_index + 1;

                end

                else begin

                    // Stop bit
                    rx_data <= data_reg;
                    rx_done <= 1;
                    receiving <= 0;
                    bit_index <= 0;

                end

            end

        end

    end

end

endmodule

rlt/uart_tx.v
module uart_tx (
    input wire clk,
    input wire rst,
    input wire tx_start,
    input wire [7:0] tx_data,
    output reg tx,
    output reg tx_busy
);

parameter CLKS_PER_BIT = 5208;

reg [7:0] data_reg;
reg [15:0] clk_count;
reg [3:0] bit_index;

always @(posedge clk) begin

    if (rst) begin
        tx <= 1;
        tx_busy <= 0;
        data_reg <= 0;
        clk_count <= 0;
        bit_index <= 0;
    end

    else if (tx_start && !tx_busy) begin
        data_reg <= tx_data;
        tx_busy <= 1;
        tx <= 0;
        bit_index <= 0;
        clk_count <= 0;
    end

    else if (tx_busy) begin

        if (clk_count < CLKS_PER_BIT - 1) begin
            clk_count <= clk_count + 1;
        end

        else begin
            clk_count <= 0;

            if (bit_index < 8) begin
                tx <= data_reg[bit_index];
                bit_index <= bit_index + 1;
            end

            else begin
                tx <= 1;
                tx_busy <= 0;
            end
        end
    end
end

endmodule

Testbench/uart_loopback_tb.v
module uart_loopback_tb;

reg clk;
reg rst;
reg tx_start;
reg [7:0] tx_data;

wire tx;
wire tx_busy;
wire [7:0] rx_data;
wire rx_done;

uart_tx #(.CLKS_PER_BIT(4)) tx_inst (
    .clk(clk),
    .rst(rst),
    .tx_start(tx_start),
    .tx_data(tx_data),
    .tx(tx),
    .tx_busy(tx_busy)
);

uart_rx #(.CLKS_PER_BIT(4)) rx_inst (
    .clk(clk),
    .rst(rst),
    .rx(tx),
    .rx_data(rx_data),
    .rx_done(rx_done)
);

always #5 clk = ~clk;

task send_byte;
    input [7:0] data;
    begin
        tx_data = data;
        tx_start = 1;

        #10;
        tx_start = 0;

        // Wait for this byte to finish
        #400;
    end
endtask

initial begin
    $dumpfile("uart_loopback.vcd");
    $dumpvars(0, uart_loopback_tb);

    clk = 0;
    rst = 1;
    tx_start = 0;
    tx_data = 8'b0;

    #20;
    rst = 0;

    // =========================
    // TEST 1
    // =========================
    send_byte(8'b10101010);

    $display("TEST 1");
    $display("Expected : 10101010");
    $display("Received : %b", rx_data);

    if (rx_data == 8'b10101010)
        $display("PASS");
    else
        $display("FAIL");

    // =========================
    // TEST 2
    // =========================
    send_byte(8'b11001100);

    $display("TEST 2");
    $display("Expected : 11001100");
    $display("Received : %b", rx_data);

    if (rx_data == 8'b11001100)
        $display("PASS");
    else
        $display("FAIL");

    // =========================
    // TEST 3
    // =========================
    send_byte(8'b11110000);

    $display("TEST 3");
    $display("Expected : 11110000");
    $display("Received : %b", rx_data);

    if (rx_data == 8'b11110000)
        $display("PASS");
    else
        $display("FAIL");

    $display("================================");
    $display("      UART LOOPBACK COMPLETE    ");
    $display("================================");

    $finish;
end

endmodule

uart_loopback.vcd
$date
	Sat Sep 12 13:27:28 2026
$end
$version
	Icarus Verilog
$end
$timescale
	1s
$end
$scope module uart_loopback_tb $end
$var wire 1 ! tx_busy $end
$var wire 1 " tx $end
$var wire 1 # rx_done $end
$var wire 8 $ rx_data [7:0] $end
$var reg 1 % clk $end
$var reg 1 & rst $end
$var reg 8 ' tx_data [7:0] $end
$var reg 1 ( tx_start $end
$scope module rx_inst $end
$var wire 1 % clk $end
$var wire 1 & rst $end
$var wire 1 " rx $end
$var parameter 32 ) CLKS_PER_BIT $end
$var reg 4 * bit_index [3:0] $end
$var reg 16 + clk_count [15:0] $end
$var reg 8 , data_reg [7:0] $end
$var reg 1 - receiving $end
$var reg 8 . rx_data [7:0] $end
$var reg 1 # rx_done $end
$upscope $end
$scope module tx_inst $end
$var wire 1 % clk $end
$var wire 1 & rst $end
$var wire 8 / tx_data [7:0] $end
$var wire 1 ( tx_start $end
$var parameter 32 0 CLKS_PER_BIT $end
$var reg 4 1 bit_index [3:0] $end
$var reg 16 2 clk_count [15:0] $end
$var reg 8 3 data_reg [7:0] $end
$var reg 1 " tx $end
$var reg 1 ! tx_busy $end
$upscope $end
$scope task send_byte $end
$var reg 8 4 data [7:0] $end
$upscope $end
$upscope $end
$enddefinitions $end
$comment Show the parameter values. $end
$dumpall
b100 0
b100 )
$end
#0
$dumpvars
bx 4
bx 3
bx 2
bx 1
b0 /
bx .
x-
bx ,
bx +
bx *
0(
b0 '
1&
0%
bx $
x#
x"
x!
$end
#5
b0 1
b0 2
b0 3
0!
1"
0-
0#
b0 $
b0 .
b0 ,
b0 *
b0 +
1%
#10
0%
#15
1%
#20
0%
1(
b10101010 '
b10101010 /
b10101010 4
0&
#25
0"
1!
b10101010 3
1%
#30
0%
0(
#35
1-
b1 2
1%
#40
0%
#45
b10 2
b1 +
1%
#50
0%
#55
b10 +
b11 2
1%
#60
0%
#65
b1 1
b0 2
b11 +
1%
#70
0%
#75
b1 *
b0 +
b1 2
1%
#80
0%
#85
b10 2
b1 +
1%
#90
0%
#95
b10 +
b11 2
1%
#100
0%
#105
b10 1
1"
b0 2
b11 +
1%
#110
0%
#115
b10 *
b10 ,
b0 +
b1 2
1%
#120
0%
#125
b10 2
b1 +
1%
#130
0%
#135
b10 +
b11 2
1%
#140
0%
#145
b11 1
0"
b0 2
b11 +
1%
#150
0%
#155
b11 *
b0 +
b1 2
1%
#160
0%
#165
b10 2
b1 +
1%
#170
0%
#175
b10 +
b11 2
1%
#180
0%
#185
b100 1
1"
b0 2
b11 +
1%
#190
0%
#195
b100 *
b1010 ,
b0 +
b1 2
1%
#200
0%
#205
b10 2
b1 +
1%
#210
0%
#215
b10 +
b11 2
1%
#220
0%
#225
b101 1
0"
b0 2
b11 +
1%
#230
0%
#235
b101 *
b0 +
b1 2
1%
#240
0%
#245
b10 2
b1 +
1%
#250
0%
#255
b10 +
b11 2
1%
#260
0%
#265
b110 1
1"
b0 2
b11 +
1%
#270
0%
#275
b110 *
b101010 ,
b0 +
b1 2
1%
#280
0%
#285
b10 2
b1 +
1%
#290
0%
#295
b10 +
b11 2
1%
#300
0%
#305
b111 1
0"
b0 2
b11 +
1%
#310
0%
#315
b111 *
b0 +
b1 2
1%
#320
0%
#325
b10 2
b1 +
1%
#330
0%
#335
b10 +
b11 2
1%
#340
0%
#345
b1000 1
1"
b0 2
b11 +
1%
#350
0%
#355
b1000 *
b10101010 ,
b0 +
b1 2
1%
#360
0%
#365
b10 2
b1 +
1%
#370
0%
#375
b10 +
b11 2
1%
#380
0%
#385
0!
b0 2
b11 +
1%
#390
0%
#395
b0 *
0-
1#
b10101010 $
b10101010 .
b0 +
1%
#400
0%
#405
0#
1%
#410
0%
#415
1%
#420
0%
#425
1%
#430
0%
1(
b11001100 '
b11001100 /
b11001100 4
#435
b0 1
0"
1!
b11001100 3
1%
#440
0%
0(
#445
b1 2
1-
1%
#450
0%
#455
b1 +
b10 2
1%
#460
0%
#465
b11 2
b10 +
1%
#470
0%
#475
b11 +
b1 1
b0 2
1%
#480
0%
#485
b1 2
b1 *
b0 +
1%
#490
0%
#495
b1 +
b10 2
1%
#500
0%
#505
b11 2
b10 +
1%
#510
0%
#515
b11 +
b10 1
b0 2
1%
#520
0%
#525
b1 2
b10 *
b10101000 ,
b0 +
1%
#530
0%
#535
b1 +
b10 2
1%
#540
0%
#545
b11 2
b10 +
1%
#550
0%
#555
b11 +
b11 1
1"
b0 2
1%
#560
0%
#565
b1 2
b11 *
b10101100 ,
b0 +
1%
#570
0%
#575
b1 +
b10 2
1%
#580
0%
#585
b11 2
b10 +
1%
#590
0%
#595
b11 +
b100 1
b0 2
1%
#600
0%
#605
b1 2
b100 *
b0 +
1%
#610
0%
#615
b1 +
b10 2
1%
#620
0%
#625
b11 2
b10 +
1%
#630
0%
#635
b11 +
b101 1
0"
b0 2
1%
#640
0%
#645
b1 2
b101 *
b0 +
1%
#650
0%
#655
b1 +
b10 2
1%
#660
0%
#665
b11 2
b10 +
1%
#670
0%
#675
b11 +
b110 1
b0 2
1%
#680
0%
#685
b1 2
b110 *
b10001100 ,
b0 +
1%
#690
0%
#695
b1 +
b10 2
1%
#700
0%
#705
b11 2
b10 +
1%
#710
0%
#715
b11 +
b111 1
1"
b0 2
1%
#720
0%
#725
b1 2
b111 *
b11001100 ,
b0 +
1%
#730
0%
#735
b1 +
b10 2
1%
#740
0%
#745
b11 2
b10 +
1%
#750
0%
#755
b11 +
b1000 1
b0 2
1%
#760
0%
#765
b1 2
b1000 *
b0 +
1%
#770
0%
#775
b1 +
b10 2
1%
#780
0%
#785
b11 2
b10 +
1%
#790
0%
#795
b11 +
0!
b0 2
1%
#800
0%
#805
b0 *
0-
1#
b11001100 $
b11001100 .
b0 +
1%
#810
0%
#815
0#
1%
#820
0%
#825
1%
#830
0%
#835
1%
#840
0%
1(
b11110000 '
b11110000 /
b11110000 4
#845
b0 1
0"
1!
b11110000 3
1%
#850
0%
0(
#855
1-
b1 2
1%
#860
0%
#865
b10 2
b1 +
1%
#870
0%
#875
b10 +
b11 2
1%
#880
0%
#885
b1 1
b0 2
b11 +
1%
#890
0%
#895
b1 *
b0 +
b1 2
1%
#900
0%
#905
b10 2
b1 +
1%
#910
0%
#915
b10 +
b11 2
1%
#920
0%
#925
b10 1
b0 2
b11 +
1%
#930
0%
#935
b10 *
b0 +
b1 2
1%
#940
0%
#945
b10 2
b1 +
1%
#950
0%
#955
b10 +
b11 2
1%
#960
0%
#965
b11 1
b0 2
b11 +
1%
#970
0%
#975
b11 *
b11001000 ,
b0 +
b1 2
1%
#980
0%
#985
b10 2
b1 +
1%
#990
0%
#995
b10 +
b11 2
1%
#1000
0%
#1005
b100 1
b0 2
b11 +
1%
#1010
0%
#1015
b100 *
b11000000 ,
b0 +
b1 2
1%
#1020
0%
#1025
b10 2
b1 +
1%
#1030
0%
#1035
b10 +
b11 2
1%
#1040
0%
#1045
b101 1
1"
b0 2
b11 +
1%
#1050
0%
#1055
b101 *
b11010000 ,
b0 +
b1 2
1%
#1060
0%
#1065
b10 2
b1 +
1%
#1070
0%
#1075
b10 +
b11 2
1%
#1080
0%
#1085
b110 1
b0 2
b11 +
1%
#1090
0%
#1095
b110 *
b11110000 ,
b0 +
b1 2
1%
#1100
0%
#1105
b10 2
b1 +
1%
#1110
0%
#1115
b10 +
b11 2
1%
#1120
0%
#1125
b111 1
b0 2
b11 +
1%
#1130
0%
#1135
b111 *
b0 +
b1 2
1%
#1140
0%
#1145
b10 2
b1 +
1%
#1150
0%
#1155
b10 +
b11 2
1%
#1160
0%
#1165
b1000 1
b0 2
b11 +
1%
#1170
0%
#1175
b1000 *
b0 +
b1 2
1%
#1180
0%
#1185
b10 2
b1 +
1%
#1190
0%
#1195
b10 +
b11 2
1%
#1200
0%
#1205
0!
b0 2
b11 +
1%
#1210
0%
#1215
b0 *
0-
1#
b11110000 $
b11110000 .
b0 +
1%
#1220
0%
#1225
0#
1%
